files_vc/__init__.py
files_vc/__main__.py
files_vc/_main.py
files_vc/types.py
files_vc/utils.py
files_vc-1.0.3.dist-info/licenses/LICENSE
files_vc-1.0.3.dist-info/METADATA
files_vc-1.0.3.dist-info/WHEEL
files_vc-1.0.3.dist-info/entry_points.txt
files_vc-1.0.3.dist-info/top_level.txt
files_vc-1.0.3.dist-info/RECORD
