Metadata-Version: 2.4
Name: Files-VC
Version: 1.0.3
Summary: A Python wrapper and CLI for the Files.VC API, designed to upload, download, and manage files efficiently.
Author-email: Sasivarnasarma <sasivarnasarma@protonmail.com>
License: MIT
Project-URL: homepage, https://github.com/Sasivarnasarma/Files-VC
Project-URL: repository, https://github.com/Sasivarnasarma/Files-VC
Project-URL: issues, https://github.com/Sasivarnasarma/Files-VC/issues
Classifier: License :: OSI Approved :: MIT License
Classifier: Operating System :: OS Independent
Classifier: Programming Language :: Python
Classifier: Programming Language :: Python :: 3
Classifier: Programming Language :: Python :: 3.7
Classifier: Programming Language :: Python :: 3.8
Classifier: Programming Language :: Python :: 3.9
Classifier: Programming Language :: Python :: 3.10
Classifier: Programming Language :: Python :: 3.11
Classifier: Programming Language :: Python :: 3.12
Requires-Python: >=3.7
License-File: LICENSE
Requires-Dist: requests
Requires-Dist: requests-toolbelt
Requires-Dist: tabulate
Dynamic: license-file
